jdw/__init__.py
jdw/jdcw.py
jdw/to_pandas.py
jdw/utils.py
jdw/version.py
jdw/data/__init__.py
jdw/data/DataAPI/__init__.py
jdw/data/DataAPI/db/__init__.py
jdw/data/DataAPI/db/db_factory.py
jdw/data/DataAPI/db/fetch_engine.py
jdw/data/DataAPI/db/utilities.py
jdw/data/DataAPI/db/kd/__init__.py
jdw/data/DataAPI/db/kd/kd_engine.py
jdw/data/DataAPI/mg/__init__.py
jdw/data/DataAPI/mg/fetch_engine.py
jdw/data/DataAPI/mg/mg_factory.py
jdw/data/DataAPI/mg/kn/__init__.py
jdw/data/DataAPI/mg/kn/kn_engine.py
jdw/data/DataAPI/rf/EVENT.py
jdw/data/DataAPI/rf/STOCK.py
jdw/data/DataAPI/rf/THEME.py
jdw/data/DataAPI/rf/__init__.py
jdw/data/ExternalAPI/__init__.py
jdw/data/ExternalAPI/datayes.py
jdw/data/ExternalAPI/ricequant.py
jdw/data/ExternalAPI/tushare.py
jdw/data/SurfaceAPI/__init__.py
jdw/data/SurfaceAPI/dummy.py
jdw/data/SurfaceAPI/engine.py
jdw/data/SurfaceAPI/factors.py
jdw/data/SurfaceAPI/index_component.py
jdw/data/SurfaceAPI/index_market.py
jdw/data/SurfaceAPI/universe.py
jdw/data/SurfaceAPI/utilities.py
jdw/data/SurfaceAPI/yields.py
jdw/data/SurfaceAPI/futures/__init__.py
jdw/data/SurfaceAPI/futures/basic.py
jdw/data/SurfaceAPI/futures/classify.py
jdw/data/SurfaceAPI/futures/factors.py
jdw/data/SurfaceAPI/futures/index_market.py
jdw/data/SurfaceAPI/futures/yields.py
jdw/data/SurfaceAPI/stock/__init__.py
jdw/data/SurfaceAPI/stock/factors.py
jdw/data/SurfaceAPI/stock/industry.py
jdw/data/SurfaceAPI/stock/market_stock.py
jdw/data/SurfaceAPI/stock/risk_model.py
jdw/data/SurfaceAPI/stock/yields.py
jdw/kdutils/__init__.py
jdw/kdutils/create_id.py
jdw/kdutils/file_utils.py
jdw/kdutils/logger.py
jdw/kdutils/singleton.py
jdw/kdutils/utils.py
jdw/kdutils/warning.py
jdw/kdutils/data/__init__.py
jdw/kdutils/data/mongodb.py
jdw/kdutils/division/__init__.py
jdw/kdutils/division/decorator.py
jdw/kdutils/division/export.py
jdw/mfc/__init__.py
jdw/mfc/anode/__init__.py
jdw/mfc/anode/axtell.py
jdw/mfc/anode/conor.py
jdw/mfc/deckard/__init__.py
jdw/mfc/deckard/goslin.py
Finance_Jindowin-1.2.5.1.dist-info/METADATA
Finance_Jindowin-1.2.5.1.dist-info/WHEEL
Finance_Jindowin-1.2.5.1.dist-info/dependency_links.txt
Finance_Jindowin-1.2.5.1.dist-info/top_level.txt
Finance_Jindowin-1.2.5.1.dist-info/RECORD
